{
  "_format": "hh-sol-cache-2",
  "files": {
    "/Users/farfama/Documents/Coding Projects/JavaScript/generative-art/contracts/Lock.sol": {
      "lastModificationDate": 1677497694473,
      "contentHash": "71406c34586c90d59a9b6540be011cc4",
      "sourceName": "contracts/Lock.sol",
      "solcConfig": {
        "version": "0.8.0",
        "settings": {
          "optimizer": {
            "enabled": true,
            "runs": 200
          },
          "outputSelection": {
            "*": {
              "*": [
                "abi",
                "evm.bytecode",
                "evm.deployedBytecode",
                "evm.methodIdentifiers",
                "metadata"
              ],
              "": [
                "ast"
              ]
            }
          }
        }
      },
      "imports": [],
      "versionPragmas": [
        "^0.8.0"
      ],
      "artifacts": [
        "Lock"
      ]
    }
  }
}
